{
  "opinions": [
    {
      "id": 1762933839760,
      "votes": 0,
      "userName": "ijaz ",
      "title": "trygifphh ",
      "body": "uhfqwep fowu fe"
    },
    {
      "id": 1762933313123,
      "votes": 0,
      "userName": "Ijaz",
      "title": "ReactJS",
      "body": "ReactJs is a framwork"
    },
    {
      "id": 1,
      "userName": "Maximilian Schwarzmüller",
      "title": "Do yourself a favor and learn React!",
      "body": "React is an amazing JavaScript library!\n\nDespite all it's shortcomings.",
      "votes": 0
    },
    {
      "id": 2,
      "userName": "Maximilian Schwarzmüller",
      "title": "React has more depth than you might first think!",
      "body": "React is a great library to learn, but it's not just about the basics. Dive deeper!\nFor example with this course!",
      "votes": 0
    }
  ]
}